__init__.py
ngit.py
util.py
commands/__init__.py
commands/git.py
executor/__init__.py
executor/executor.py
ngit_cli-0.0.1.dist-info/licenses/LICENSE
translator/__init__.py
translator/offline_translator.py
translator/translator_util.py
ngit_cli-0.0.1.dist-info/METADATA
ngit_cli-0.0.1.dist-info/WHEEL
ngit_cli-0.0.1.dist-info/entry_points.txt
ngit_cli-0.0.1.dist-info/top_level.txt
ngit_cli-0.0.1.dist-info/RECORD
