Metadata-Version: 2.4
Name: ngit-cli
Version: 0.0.1
Summary: A simple CLI tool to run custom commands
Author-email: A F M Mohimenul Joaa <mohimenul.joaa@gmail.com>
License: GNU
Project-URL: Homepage, https://github.com/faerber-lab/ngit-cli
Requires-Python: >=3.6
License-File: LICENSE
Requires-Dist: torch==2.7.0+cpu
Requires-Dist: click~=8.1.8
Requires-Dist: prompt_toolkit~=3.0.51
Requires-Dist: yaspin~=3.1.0
Dynamic: license-file
